MANIFEST.in
README.md
setup.cfg
setup.py
pyapex/__init__.py
pyapex/main.py
pyapex/pyapex.py
pyapex/run.py
pyapex/template.html
pyapex.egg-info/PKG-INFO
pyapex.egg-info/SOURCES.txt
pyapex.egg-info/dependency_links.txt
pyapex.egg-info/requires.txt
pyapex.egg-info/top_level.txt
pyapex/html/.DS_Store
pyapex/html/54839aab-881d-4392-81b7-90ec0d41ebe3.html
pyapex/html/assets/.DS_Store
pyapex/html/assets/main.css
pyapex/html/assets/apex/.DS_Store
pyapex/html/assets/apex/apexcharts.amd.js
pyapex/html/assets/apex/apexcharts.amd.js.LICENSE.txt
pyapex/html/assets/apex/apexcharts.common.js
pyapex/html/assets/apex/apexcharts.css
pyapex/html/assets/apex/apexcharts.esm.js
pyapex/html/assets/apex/apexcharts.js
pyapex/html/assets/apex/apexcharts.min.js
pyapex/html/assets/apex/locales/ca.json
pyapex/html/assets/apex/locales/cs.json
pyapex/html/assets/apex/locales/de.json
pyapex/html/assets/apex/locales/el.json
pyapex/html/assets/apex/locales/en.json
pyapex/html/assets/apex/locales/es.json
pyapex/html/assets/apex/locales/fi.json
pyapex/html/assets/apex/locales/fr.json
pyapex/html/assets/apex/locales/he.json
pyapex/html/assets/apex/locales/hi.json
pyapex/html/assets/apex/locales/hr.json
pyapex/html/assets/apex/locales/hy.json
pyapex/html/assets/apex/locales/id.json
pyapex/html/assets/apex/locales/it.json
pyapex/html/assets/apex/locales/ja.json
pyapex/html/assets/apex/locales/ka.json
pyapex/html/assets/apex/locales/ko.js
pyapex/html/assets/apex/locales/ko.json
pyapex/html/assets/apex/locales/lt.json
pyapex/html/assets/apex/locales/nb.json
pyapex/html/assets/apex/locales/nl.json
pyapex/html/assets/apex/locales/pl.json
pyapex/html/assets/apex/locales/pt-br.json
pyapex/html/assets/apex/locales/pt.json
pyapex/html/assets/apex/locales/rs.json
pyapex/html/assets/apex/locales/ru.json
pyapex/html/assets/apex/locales/se.json
pyapex/html/assets/apex/locales/sk.json
pyapex/html/assets/apex/locales/sl.json
pyapex/html/assets/apex/locales/sq.json
pyapex/html/assets/apex/locales/th.json
pyapex/html/assets/apex/locales/tr.json
pyapex/html/assets/apex/locales/ua.json
pyapex/html/assets/apex/locales/zh-cn.json