Metadata-Version: 2.1
Name: pyapex
Version: 0.0.4
Summary: Create interactive html charts
Home-page: https://github.com/nicodemus-opon/pyapex
Author: nicodemus opon
Author-email: hello@nicopon.me
License: MIT
Download-URL: https://github.com/nicodemus-opon/pyapex/archive/refs/tags/v_0.0.4.tar.gz
Keywords: chart,plotting
Platform: UNKNOWN
Classifier: Development Status :: 4 - Beta
Classifier: Intended Audience :: Science/Research
Classifier: Topic :: Scientific/Engineering :: Visualization
Classifier: License :: OSI Approved :: MIT License
Classifier: Programming Language :: Python :: 3
Classifier: Programming Language :: Python :: 3.4
Classifier: Programming Language :: Python :: 3.5
Classifier: Programming Language :: Python :: 3.6
